{"status_code":10,"lang":"python3","run_success":true,"status_runtime":"1 ms","memory":17284000,"display_runtime":"1","question_id":"1812","elapsed_time":59,"compare_result":"111111111111111111111111111111111111111111111111111111111111111111111111111111111111111111111111111111111111","code_output":"","std_output":"","last_testcase":"","expected_output":"","task_finish_time":1733686483877,"task_name":"judger.judgetask.Judge","finished":true,"total_correct":108,"total_testcases":108,"runtime_percentile":13.023300000000006,"status_memory":"17.3 MB","memory_percentile":10.64520000000001,"pretty_lang":"Python3","submission_id":"1473753054","status_msg":"Accepted","state":"SUCCESS"}