{"status_code":10,"lang":"python3","run_success":true,"status_runtime":"43 ms","memory":18832000,"question_id":"1665","elapsed_time":68,"compare_result":"11111111111111111111111111111111111111","code_output":"","std_output":"","last_testcase":"","expected_output":"","task_finish_time":1733716011571,"task_name":"judger.judgetask.Judge","finished":true,"total_correct":38,"total_testcases":38,"runtime_percentile":73.68429999999996,"status_memory":"18.8 MB","memory_percentile":6.602000000000002,"pretty_lang":"Python3","submission_id":"1473973415","status_msg":"Accepted","state":"SUCCESS"}