{"status_code":10,"lang":"python3","run_success":true,"status_runtime":"41 ms","memory":17136000,"question_id":"1205","elapsed_time":54,"compare_result":"11111111111111111111111111111111111111111111111111111111111111","code_output":"","std_output":"","last_testcase":"","expected_output":"","task_finish_time":1733689501902,"task_name":"judger.judgetask.Judge","finished":true,"total_correct":62,"total_testcases":62,"runtime_percentile":13.065700000000012,"status_memory":"17.1 MB","memory_percentile":12.938700000000003,"pretty_lang":"Python3","submission_id":"1473780283","status_msg":"Accepted","state":"SUCCESS"}